{
"meta":{"test_sets":[],"test_metrics":[],"learn_metrics":[{"best_value":"Min","name":"RMSE"}],"launch_mode":"Train","parameters":"","iteration_count":3000,"learn_sets":["learn"],"name":"experiment"},
"iterations":[
{"learn":[9.862055921],"iteration":0,"passed_time":0.1000915174,"remaining_time":300.1744606},
{"learn":[9.708469939],"iteration":1,"passed_time":0.2145424634,"remaining_time":321.5991526},
{"learn":[9.56158426],"iteration":2,"passed_time":0.3408706448,"remaining_time":340.5297741},
{"learn":[9.428246475],"iteration":3,"passed_time":0.4722467093,"remaining_time":353.7127853},
{"learn":[9.292066384],"iteration":4,"passed_time":0.6088594815,"remaining_time":364.7068294},
{"learn":[9.153502301],"iteration":5,"passed_time":0.7044202622,"remaining_time":351.5057108},
{"learn":[9.029312357],"iteration":6,"passed_time":0.8057086489,"remaining_time":344.497998},
{"learn":[8.899751908],"iteration":7,"passed_time":0.8999057758,"remaining_time":336.5647602},
{"learn":[8.772501693],"iteration":8,"passed_time":0.9957021731,"remaining_time":330.9050222},
{"learn":[8.653368923],"iteration":9,"passed_time":1.097330421,"remaining_time":328.101796},
{"learn":[8.538820069],"iteration":10,"passed_time":1.185713905,"remaining_time":322.1908055},
{"learn":[8.424640323],"iteration":11,"passed_time":1.271849227,"remaining_time":316.6904576},
{"learn":[8.310588656],"iteration":12,"passed_time":1.380790642,"remaining_time":317.2632038},
{"learn":[8.204626292],"iteration":13,"passed_time":1.460809417,"remaining_time":311.5697798},
{"learn":[8.095753545],"iteration":14,"passed_time":1.547081817,"remaining_time":307.8692815},
{"learn":[7.997518418],"iteration":15,"passed_time":1.647545527,"remaining_time":307.2672408},
{"learn":[7.898274558],"iteration":16,"passed_time":1.783244586,"remaining_time":312.9069764},
{"learn":[7.798846285],"iteration":17,"passed_time":1.89292793,"remaining_time":313.5950603},
{"learn":[7.702393805],"iteration":18,"passed_time":1.978701725,"remaining_time":310.4478864},
{"learn":[7.615583013],"iteration":19,"passed_time":2.072137632,"remaining_time":308.7485071},
{"learn":[7.526800233],"iteration":20,"passed_time":2.174492393,"remaining_time":308.4672781},
{"learn":[7.440039151],"iteration":21,"passed_time":2.260113528,"remaining_time":305.9371858},
{"learn":[7.353218709],"iteration":22,"passed_time":2.354299364,"remaining_time":304.7282263},
{"learn":[7.265960362],"iteration":23,"passed_time":2.443852591,"remaining_time":303.0377213},
{"learn":[7.184184162],"iteration":24,"passed_time":2.5410086,"remaining_time":302.3800235},
{"learn":[7.107823349],"iteration":25,"passed_time":2.646842264,"remaining_time":302.7580344},
{"learn":[7.031958198],"iteration":26,"passed_time":2.740165467,"remaining_time":301.7226642},
{"learn":[6.960967565],"iteration":27,"passed_time":2.827514199,"remaining_time":300.1204357},
{"learn":[6.889928157],"iteration":28,"passed_time":2.908495602,"remaining_time":297.9703598},
{"learn":[6.830265889],"iteration":29,"passed_time":2.995137571,"remaining_time":296.5186195},
{"learn":[6.766646873],"iteration":30,"passed_time":3.08014198,"remaining_time":294.9981142}
]}